html5-0.0.9.dist-info/DESCRIPTION.rst
html5-0.0.9.dist-info/METADATA
html5-0.0.9.dist-info/RECORD
html5-0.0.9.dist-info/WHEEL
html5-0.0.9.dist-info/metadata.json
html5-0.0.9.dist-info/top_level.txt
html5lib/__init__.py
html5lib/_ihatexml.py
html5lib/_inputstream.py
html5lib/_tokenizer.py
html5lib/_utils.py
html5lib/constants.py
html5lib/html5parser.py
html5lib/serializer.py
html5lib/_trie/__init__.py
html5lib/_trie/_base.py
html5lib/_trie/datrie.py
html5lib/_trie/py.py
html5lib/filters/__init__.py
html5lib/filters/alphabeticalattributes.py
html5lib/filters/base.py
html5lib/filters/inject_meta_charset.py
html5lib/filters/lint.py
html5lib/filters/optionaltags.py
html5lib/filters/sanitizer.py
html5lib/filters/whitespace.py
html5lib/treeadapters/__init__.py
html5lib/treeadapters/genshi.py
html5lib/treeadapters/sax.py
html5lib/treebuilders/__init__.py
html5lib/treebuilders/base.py
html5lib/treebuilders/dom.py
html5lib/treebuilders/etree.py
html5lib/treebuilders/etree_lxml.py
html5lib/treewalkers/__init__.py
html5lib/treewalkers/base.py
html5lib/treewalkers/dom.py
html5lib/treewalkers/etree.py
html5lib/treewalkers/etree_lxml.py
html5lib/treewalkers/genshi.py
